{"2023-6":[{"title":"django框架","date":"2023-06-16T07:21:43.000Z","link":"//wuqiuxu.github.io/post/ca694513.html"},{"title":"kafka环境配置及开发","date":"2023-06-16T11:33:53.000Z","link":"//wuqiuxu.github.io/post/3575b0ed.html"},{"title":"IDEA的安装和使用","date":"2023-06-19T13:47:57.000Z","link":"//wuqiuxu.github.io/post/b9f49ee0.html"},{"title":"Pandas基本概念及使用指南","date":"2023-06-19T13:50:43.000Z","link":"//wuqiuxu.github.io/post/4b35f5df.html"},{"title":"Shell基本概念及语法","date":"2023-06-19T13:51:02.000Z","link":"//wuqiuxu.github.io/post/41a4bcc7.html"},{"title":"HBase基本概念及原理","date":"2023-06-19T13:51:20.000Z","link":"//wuqiuxu.github.io/post/d11c245e.html"},{"title":"Request基本概念及使用方法","date":"2023-06-19T13:51:55.000Z","link":"//wuqiuxu.github.io/post/aef1d83e.html"},{"title":"基于Hexo框架搭建个人博客","date":"2023-06-19T13:53:33.000Z","link":"//wuqiuxu.github.io/post/9a55b595.html"},{"title":"selenium模块常用属性及方法","date":"2023-06-20T03:25:57.000Z","link":"//wuqiuxu.github.io/post/d87f7e0c.html"},{"title":"Java概述","date":"2023-06-20T13:46:10.000Z","link":"//wuqiuxu.github.io/post/1113d944.html"},{"title":"Java基础语法","date":"2023-06-20T13:46:30.000Z","link":"//wuqiuxu.github.io/post/ea538f2a.html"},{"title":"Java流程控制","date":"2023-06-20T13:46:37.000Z","link":"//wuqiuxu.github.io/post/41201b24.html"},{"title":"Java数组","date":"2023-06-20T13:46:43.000Z","link":"//wuqiuxu.github.io/post/e3345db4.html"},{"title":"Java面向对象及三大特性","date":"2023-06-20T13:47:07.000Z","link":"//wuqiuxu.github.io/post/6d54f4ae.html"},{"title":"Java枚举、接口和注解","date":"2023-06-20T13:47:17.000Z","link":"//wuqiuxu.github.io/post/76720176.html"},{"title":"Java异常","date":"2023-06-20T13:47:31.000Z","link":"//wuqiuxu.github.io/post/f495a96f.html"},{"title":"Java多线程","date":"2023-06-20T13:47:36.000Z","link":"//wuqiuxu.github.io/post/a2c3ad19.html"},{"title":"Java集合","date":"2023-06-20T13:47:40.000Z","link":"//wuqiuxu.github.io/post/4509351.html"},{"title":"Java泛型","date":"2023-06-20T13:47:45.000Z","link":"//wuqiuxu.github.io/post/a14eb637.html"},{"title":"Java IO流","date":"2023-06-20T13:47:50.000Z","link":"//wuqiuxu.github.io/post/59ae8782.html"},{"title":"Java网络编程","date":"2023-06-20T13:47:56.000Z","link":"//wuqiuxu.github.io/post/3a3aa666.html"},{"title":"Java反射","date":"2023-06-20T13:48:00.000Z","link":"//wuqiuxu.github.io/post/fa358471.html"},{"title":"Java正则表达式","date":"2023-06-20T13:48:11.000Z","link":"//wuqiuxu.github.io/post/4ea1809c.html"},{"title":"Java常用API","date":"2023-06-20T13:48:19.000Z","link":"//wuqiuxu.github.io/post/1630b670.html"},{"title":"Linux概述及常用命令","date":"2023-06-20T14:39:54.000Z","link":"//wuqiuxu.github.io/post/2c831fb.html"}]}